{
  "color": {
    "base": {
      "black": {
        "alpha": { "value": "#0C0C0C" },
        "beta": { "value": "#0B1215" },
        "gamma": { "value": "#0D1717" },
        "epsilon": { "value": "#101720" },
        "theta": { "value": "#171717" },
        "eta": { "value": "#011222" },
        "iota": { "value": "#020D19" }
      },
      "white": {
        "alpha": {
          "value": "#fff"
        }
      },
      "purple": {
        "dark": {
          "alpha": { "value": "#f189ff" },
          "beta": { "value": "#ee6bff" },
          "gamma": { "value": "#ea46ff" }
        }
      },
      "green": {
        "dark": {
          "alpha": { "value": "#69dc9e" }
        }
      },
      "blue": {
        "dark": {
          "alpha": { "value": "#9eb7e5" }
        },
        "light": {
          "alpha": { "value": "#c6e0ff" }
        }
      },
      "red": {
        "light": {
          "alpha": { "value": "#e63946" },
          "beta": { "value": "#d62828" }
        }
      }
    }
  }
}
